[
  {
    "name": "Fuji 3513",
    "data": {
      "c": {
        "colorMix": 1,
        "lumaMix": 1,
        "lut": null,
        "referenceID": "dZ8IUECXuQAl",
        "sourceID": "",
        "sourceIDT": "sRGB"
      },
      "s": {
        "colorVolume": [
          0.7713393876833875,
          0.6965941030682321
        ],
        "colorBalance": [
          0.44567831415268383,
          0.6225614061807709
        ],
        "shadows": [
          0.5786153523278125,
          0.3036424933094325
        ],
        "highlights": [
          0.5798130722278738,
          0.6826181809511699
        ],
        "shadowMapVectors": [
          [
            22.803254112426657,
            1.265158139622484
          ],
          [
            46.507447380411634,
            0.9478180513930937
          ],
          [
            108.52439469075006,
            1.001921822522846
          ],
          [
            185.79497658400754,
            0.9106187221170705
          ],
          [
            202.66173330417536,
            0.8958336967418987
          ],
          [
            335.1015850716303,
            0.815279384479049
          ]
        ],
        "highlightMapVectors": [
          [
            11.879494592670198,
            0.9155663223888222
          ],
          [
            50.26181155294768,
            0.6136806200085839
          ],
          [
            111.61947224073685,
            0.622490935183268
          ],
          [
            190.18276764686823,
            0.6964534788278479
          ],
          [
            234.94197449588756,
            0.6116827390056276
          ],
          [
            331.0536925621873,
            0.581577005594166
          ]
        ],
        "separation": 0.315
      },
      "d": {
        "hueVsDensity": [
          [
            0,
            0.5
          ],
          [
            0.167,
            0.5
          ],
          [
            0.333,
            0.5
          ],
          [
            0.583,
            0.5
          ],
          [
            0.805,
            0.5
          ],
          [
            1,
            0.5
          ]
        ],
        "hvdInterpolation": "Bezier",
        "chromaVsDensity": [
          [
            0,
            0.33729640305707076
          ],
          [
            0.3499747971047677,
            0.47549299590897987
          ],
          [
            0.6972265684628302,
            0.414146139481397
          ],
          [
            1,
            0.19053655218899868
          ]
        ],
        "cvdInterpolation": "Cubic",
        "lumaVsDensity": [
          [
            0.00572511194219712,
            0.15414152181877394
          ],
          [
            0.2316877512339083,
            0.25224172891394614
          ],
          [
            0.442240847453315,
            0.5044618324106489
          ],
          [
            0.6700817782272427,
            0.26912004905153464
          ],
          [
            1,
            0.13448210941952288
          ]
        ],
        "lvdInterpolation": "Cubic"
      },
      "l": {
        "lumaVsLuma": [
          [
            0,
            0
          ],
          [
            0.31750877728591054,
            0.21490640010583728
          ],
          [
            0.46405128987940775,
            0.5766676694923878
          ],
          [
            0.762809351625706,
            0.8020261425852805
          ],
          [
            1,
            0.8089659933953431
          ]
        ],
        "lvlInterpolation": "Cubic",
        "hueVsLuma": [
          [
            0,
            0.7437912791052674
          ],
          [
            0.18339975926067267,
            0.6106893801392168
          ],
          [
            0.3814398565104564,
            0.5896243156191484
          ],
          [
            0.5389507963160841,
            0.694534939041765
          ],
          [
            0.8080576915738056,
            0.5687347986037613
          ],
          [
            1,
            0.7437912791052674
          ]
        ],
        "hvlInterpolation": "Bezier",
        "expVsLuma": [
          [
            0,
            0.5
          ],
          [
            0.333,
            0.5
          ],
          [
            0.667,
            0.5
          ],
          [
            1,
            0.5
          ]
        ],
        "evlInterpolation": "Cubic",
        "blackPoint": [
          0.63,
          0.89,
          0.7999999999999999
        ],
        "whitePoint": [
          0.38,
          0.36,
          0.4
        ],
        "bpLinked": false,
        "wpLinked": false
      },
      "r": {
        "acutanceAmount": 0.15,
        "filmResolution": 0.5,
        "grainDensity": 0.1,
        "grainChroma": 0.35,
        "halationMix": 0.2,
        "halationHue": 0.88,
        "halationSat": 0.3,
        "halationSpl": 0.2,
        "diffusionAmount": 0,
        "diffusionThreshold": 0,
        "diffusionFadeLevel": 0,
        "diffusionCenterProtection": 0,
        "diffusionCenter": [
          0.5,
          0.5
        ],
        "spotlightAmount": 0.25,
        "spotlightContrast": 0.5,
        "spotlightBias": 0.5,
        "spotlightFocus": 0.5,
        "spotlightCenter": [
          0.5,
          0.5
        ]
      },
      "g": {
        "presetID": "45033b3d-486e-4230-b595-dceec9e14502"
      }
    },
    "meta": {
      "description": ""
    }
  }
]